cvss_util/__init__.py
cvss_util/cli.py
cvss_util/cvssv2/__init__.py
cvss_util/cvssv2/calculator.py
cvss_util/cvssv2/test.py
cvss_util/cvssv3/__init__.py
cvss_util/cvssv3/calculator.py
cvss_util/cvssv3/test.py
cvss_util/utils/__init__.py
cvss_util/utils/create_cvss_format.py
cvss_util/utils/parse_cvss_format.py
cvss_util/utils/test.py
cvss_util-2.4.1.dist-info/AUTHORS
cvss_util-2.4.1.dist-info/LICENSE
cvss_util-2.4.1.dist-info/METADATA
cvss_util-2.4.1.dist-info/WHEEL
cvss_util-2.4.1.dist-info/pbr.json
cvss_util-2.4.1.dist-info/top_level.txt
cvss_util-2.4.1.dist-info/RECORD
